{
  "db": [
    {
      "firstname": "Alexis",
      "lastname": "Contente",
      "email": "alexis.contente@gmail.com",
      "birth": "1993-04-21",
      "informations": "Dev web to the top",
      "id": 1
    },
    {
      "firstname": "aaaa",
      "lastname": "aaaa",
      "email": "aaaaa",
      "birth": "1993-04-21",
      "informations": "",
      "id": 2
    },
    {
      "firstname": "aaaa",
      "lastname": "aaaa",
      "email": "aaaa",
      "birth": "1993-04-21",
      "informations": "",
      "id": 3
    }
  ]
}